{
  "info": {
    "url_png_icon_64x64": "https://raw.githubusercontent.com/stakepoolonline/stakepool.at/main/apple-icon-60x60.png,
    "url_png_logo": "https://raw.githubusercontent.com/stakepoolonline/stakepool.at/main/ms-icon-150x150.png",
    "location": "Austria, Europe",
    "social": {
      "twitter_handle": "ATADA_Stakepool",
      "telegram_handle": "atada_stakepool_austria",
      "facebook_handle": "ATADA.StakePool.Austria",
      "youtube_handle": "",
      "twitch_handle": "",
      "discord_handle": "",
      "github_handle": "gitmachtl"
    },
    "company": {
      "name": "",
      "addr": "",
      "city": "",
      "country": "",
      "company_id": "",
      "vat_id": ""
    },
    "about": {
      "me": "ATADA is a Stakepool-Operator-Supporter Pool and located in the beautiful DACH Area Austria/Germany/Switzerland. Please come and join us by delegating to ATADA! :-)",
      "server": "Dedicate Server(s), Dual Xeon Platform, 1Gbit backbone, 10Gbit upgrade possible, ...",
      "company": ""
    },
    "rss": ""
  },
  "telegram-admin-handle": {
    "0": "atada_stakepool"
  },
  "my-pool-ids": {
    "0": "2ba96bc27be2bdde3ec11b9f696cf21fad39e49097be9b0193e6b572",
    "1": "00000036d515e12e18cd3c88c74f09a67984c2c279a5296aa96efe89"
  },
  "when-satured-then-recommend": {
    "0": "00000036d515e12e18cd3c88c74f09a67984c2c279a5296aa96efe89"
  }
}
